COPYING.txt
INSTALL.txt
MANIFEST.in
README.txt
ez_setup.py
setup.py
doc/README.txt
doc/mwavepy.pdf
doc/api/generate_docs.py
doc/api/mwavepy.beta.html
doc/api/mwavepy.beta.mobius.html
doc/api/mwavepy.beta.onePortCalibrationGui.html
doc/api/mwavepy.beta.plot.html
doc/api/mwavepy.beta.testCases.html
doc/api/mwavepy.calibration.html
doc/api/mwavepy.convenience.html
doc/api/mwavepy.frequency.html
doc/api/mwavepy.html
doc/api/mwavepy.mathFunctions.html
doc/api/mwavepy.media.cpw.html
doc/api/mwavepy.media.distributedCircuit.html
doc/api/mwavepy.media.freespace.html
doc/api/mwavepy.media.html
doc/api/mwavepy.media.media.html
doc/api/mwavepy.media.rectangularWaveguide.html
doc/api/mwavepy.network.html
doc/api/mwavepy.plotting.html
doc/api/mwavepy.testCases.html
doc/api/mwavepy.testCases.testCalibration.html
doc/api/mwavepy.testCases.testMedia.html
doc/api/mwavepy.testCases.testNetwork.html
doc/api/mwavepy.testCases.testTransmissionLine.html
doc/api/mwavepy.testCases.testWorkingBand.html
doc/api/mwavepy.tlineFunctions.html
doc/api/mwavepy.touchstone.html
doc/api/mwavepy.virtualInstruments.futekLoadCell.html
doc/api/mwavepy.virtualInstruments.generalSocketReader.html
doc/api/mwavepy.virtualInstruments.html
doc/html/.buildinfo
doc/html/architecture.html
doc/html/calibration.html
doc/html/circuit_design.html
doc/html/examples.html
doc/html/genindex.html
doc/html/index.html
doc/html/installation.html
doc/html/objects.inv
doc/html/py-modindex.html
doc/html/quick_intro.html
doc/html/search.html
doc/html/searchindex.js
doc/html/slow_intro.html
doc/html/_images/ComplexDrift.png
doc/html/_images/FFTofPhaseDrift.png
doc/html/_images/PhaseDriftDistrobution.png
doc/html/_images/PhaseDriftvsTime.png
doc/html/_images/Return_Loss(Mag).png
doc/html/_images/Return_Loss(Phase).png
doc/html/_images/Return_Loss(Polar).png
doc/html/_images/Return_Loss(Smith).png
doc/html/_images/Return_Loss(Unwrapped_Phase).png
doc/html/_images/Series-Shunt_Stub_Matching_2D.png
mwavepy.egg-info/PKG-INFO
mwavepy.egg-info/SOURCES.txt
mwavepy.egg-info/dependency_links.txt
mwavepy.egg-info/top_level.txt
