Metadata-Version: 1.0
Name: mwavepy
Version: 1.5
Summary: Object Oriented Microwave Engineering
Home-page: http://code.google.com/p/mwavepy/
Author: Alex Arsenovic
Author-email: arsenovic@virginia.edu
License: gpl
Platform: UNKNOWN
